sumogsuitealertscollector/__init__.py
sumogsuitealertscollector/gsuitealertcenter.yaml
sumogsuitealertscollector/main.py
sumogsuitealertscollector/common/__init__.py
sumogsuitealertscollector/common/config.py
sumogsuitealertscollector/common/logger.py
sumogsuitealertscollector/common/mixin.py
sumogsuitealertscollector/omnistorage/__init__.py
sumogsuitealertscollector/omnistorage/aws.py
sumogsuitealertscollector/omnistorage/azure.py
sumogsuitealertscollector/omnistorage/base.py
sumogsuitealertscollector/omnistorage/errors.py
sumogsuitealertscollector/omnistorage/factory.py
sumogsuitealertscollector/omnistorage/gcp.py
sumogsuitealertscollector/omnistorage/onprem.py
sumogsuitealertscollector/sumoclient/__init__.py
sumogsuitealertscollector/sumoclient/base.py
sumogsuitealertscollector/sumoclient/factory.py
sumogsuitealertscollector/sumoclient/httputils.py
sumogsuitealertscollector/sumoclient/outputhandlers.py
sumogsuitealertscollector/sumoclient/utils.py
sumologic_gsuitealertcenter-1.0.6.dist-info/LICENSE
sumologic_gsuitealertcenter-1.0.6.dist-info/METADATA
sumologic_gsuitealertcenter-1.0.6.dist-info/WHEEL
sumologic_gsuitealertcenter-1.0.6.dist-info/entry_points.txt
sumologic_gsuitealertcenter-1.0.6.dist-info/top_level.txt
sumologic_gsuitealertcenter-1.0.6.dist-info/zip-safe
sumologic_gsuitealertcenter-1.0.6.dist-info/RECORD
