Metadata-Version: 2.1
Name: sumologic-gsuitealertcenter
Version: 1.0.6
Summary: Sumo Logic collection solution for G Suite Alert Center
Home-page: https://github.com/SumoLogic/sumologic-gsuitealertcenter
Author: SumoLogic
Author-email: it@sumologic.com, apps-team@sumologic.com
License: PSF
Keywords: sumologic python rest api log management analytics logreduce g suite agent security siem collector forwarder
Platform: UNKNOWN
Classifier: Development Status :: 4 - Beta
Classifier: Intended Audience :: Developers
Classifier: Programming Language :: Python :: 2.7
Classifier: Programming Language :: Python :: 3.7
Classifier: Operating System :: OS Independent
Requires-Dist: requests (==2.21.0)
Requires-Dist: PyYAML (==5.1)
Requires-Dist: future-fstrings (==0.4.5)
Requires-Dist: futures (==3.1.1)
Requires-Dist: six (==1.12.0)
Requires-Dist: google-api-python-client (==1.7.8)
Requires-Dist: oauth2client (==4.1.3)
Requires-Dist: google-cloud-datastore (==1.7.3)
Requires-Dist: futures ; python_version < "3.2"
Requires-Dist: future-fstrings ; python_version < "3.6"
